{
  "manifestVersion": "3.2",
  "admin": {
    "address": "0xc8c613CbaD9AD8B97c45602590f87dcB99e00b7F",
    "txHash": "0x73fc9f555b6d7b1782b926d4eee914773c85c4406d7ea80c0151bc308c3d3179"
  },
  "proxies": [
    {
      "address": "0x48B892923d6Fe5798c93C7b09e0842C9C7f69249",
      "txHash": "0x86dd3733494e06251c05e44c51b593ea4f51d2f2a9de44b3e122a09cd2a56672",
      "kind": "transparent"
    },
    {
      "address": "0x985f4C5E9212570d531b06293f4e69c064B23fC1",
      "txHash": "0x55bd54212b36a5eb9890dd2bb2fef3221fc40c1a2c4f85b4c57194e402bae983",
      "kind": "transparent"
    },
    {
      "address": "0x38B07FBFb2aB88FCde99aFF7d964Fb752aEA652c",
      "txHash": "0x03935115725a69599b8625dcdfeb0bcb14ab0ff238405a469e6938112f3f4aca",
      "kind": "transparent"
    }
  ],
  "impls": {
    "e2cb171a27c4fad01a5fd96ac6d7a39871ea274a9b82d41c9bcc7a6f1107f5f5": {
      "address": "0x5803C0CDD0234AB52144F1Eb0D2B9a56de85f5E1",
      "txHash": "0xc42fb0cc19e154f20c0ae946d9e75667c851e2b24eb7e31372a6ab3e85d6b829",
      "layout": {
        "storage": [
          {
            "label": "_initialized",
            "offset": 0,
            "slot": "0",
            "type": "t_bool",
            "contract": "Initializable",
            "src": "@openzeppelin/contracts-upgradeable/proxy/utils/Initializable.sol:39"
          },
          {
            "label": "_initializing",
            "offset": 1,
            "slot": "0",
            "type": "t_bool",
            "contract": "Initializable",
            "src": "@openzeppelin/contracts-upgradeable/proxy/utils/Initializable.sol:44"
          },
          {
            "label": "__gap",
            "offset": 0,
            "slot": "1",
            "type": "t_array(t_uint256)50_storage",
            "contract": "ContextUpgradeable",
            "src": "@openzeppelin/contracts-upgradeable/utils/ContextUpgradeable.sol:36"
          },
          {
            "label": "_owner",
            "offset": 0,
            "slot": "51",
            "type": "t_address",
            "contract": "OwnableUpgradeable",
            "src": "@openzeppelin/contracts-upgradeable/access/OwnableUpgradeable.sol:22"
          },
          {
            "label": "__gap",
            "offset": 0,
            "slot": "52",
            "type": "t_array(t_uint256)49_storage",
            "contract": "OwnableUpgradeable",
            "src": "@openzeppelin/contracts-upgradeable/access/OwnableUpgradeable.sol:87"
          }
        ],
        "types": {
          "t_address": {
            "label": "address",
            "numberOfBytes": "20"
          },
          "t_array(t_uint256)49_storage": {
            "label": "uint256[49]",
            "numberOfBytes": "1568"
          },
          "t_array(t_uint256)50_storage": {
            "label": "uint256[50]",
            "numberOfBytes": "1600"
          },
          "t_bool": {
            "label": "bool",
            "numberOfBytes": "1"
          },
          "t_uint256": {
            "label": "uint256",
            "numberOfBytes": "32"
          }
        }
      }
    },
    "fefd42630865960e9b2fdd98d480c3ddb66e5ac3177e4da99a3aa44f04ce52e5": {
      "address": "0x5fD35194C14398786729947F95c4067D0e686139",
      "txHash": "0x04c920fd397fb6d11e5eb50c8e1c6a19fa3595f743db4e0cd257f7151030c66d",
      "layout": {
        "storage": [
          {
            "label": "_initialized",
            "offset": 0,
            "slot": "0",
            "type": "t_bool",
            "contract": "Initializable",
            "src": "@openzeppelin/contracts-upgradeable/proxy/utils/Initializable.sol:39"
          },
          {
            "label": "_initializing",
            "offset": 1,
            "slot": "0",
            "type": "t_bool",
            "contract": "Initializable",
            "src": "@openzeppelin/contracts-upgradeable/proxy/utils/Initializable.sol:44"
          },
          {
            "label": "__gap",
            "offset": 0,
            "slot": "1",
            "type": "t_array(t_uint256)50_storage",
            "contract": "ContextUpgradeable",
            "src": "@openzeppelin/contracts-upgradeable/utils/ContextUpgradeable.sol:36"
          },
          {
            "label": "_owner",
            "offset": 0,
            "slot": "51",
            "type": "t_address",
            "contract": "OwnableUpgradeable",
            "src": "@openzeppelin/contracts-upgradeable/access/OwnableUpgradeable.sol:22"
          },
          {
            "label": "__gap",
            "offset": 0,
            "slot": "52",
            "type": "t_array(t_uint256)49_storage",
            "contract": "OwnableUpgradeable",
            "src": "@openzeppelin/contracts-upgradeable/access/OwnableUpgradeable.sol:87"
          }
        ],
        "types": {
          "t_address": {
            "label": "address",
            "numberOfBytes": "20"
          },
          "t_array(t_uint256)49_storage": {
            "label": "uint256[49]",
            "numberOfBytes": "1568"
          },
          "t_array(t_uint256)50_storage": {
            "label": "uint256[50]",
            "numberOfBytes": "1600"
          },
          "t_bool": {
            "label": "bool",
            "numberOfBytes": "1"
          },
          "t_uint256": {
            "label": "uint256",
            "numberOfBytes": "32"
          }
        }
      }
    },
    "998d0e790de38b6a08e1f19ea1e85e898f96dbef19d79643653d7d2ac78b7703": {
      "address": "0x65598AaB2B0101B392cB3380245152ECf01aF3da",
      "txHash": "0xd29ff0b5d3b1b654b719dbc7fca8fbd6270e6951f01a2ce95820ad443120a655",
      "layout": {
        "storage": [
          {
            "label": "_initialized",
            "offset": 0,
            "slot": "0",
            "type": "t_bool",
            "contract": "Initializable",
            "src": "@openzeppelin/contracts-upgradeable/proxy/utils/Initializable.sol:39"
          },
          {
            "label": "_initializing",
            "offset": 1,
            "slot": "0",
            "type": "t_bool",
            "contract": "Initializable",
            "src": "@openzeppelin/contracts-upgradeable/proxy/utils/Initializable.sol:44"
          },
          {
            "label": "__gap",
            "offset": 0,
            "slot": "1",
            "type": "t_array(t_uint256)50_storage",
            "contract": "ContextUpgradeable",
            "src": "@openzeppelin/contracts-upgradeable/utils/ContextUpgradeable.sol:36"
          },
          {
            "label": "_owner",
            "offset": 0,
            "slot": "51",
            "type": "t_address",
            "contract": "OwnableUpgradeable",
            "src": "@openzeppelin/contracts-upgradeable/access/OwnableUpgradeable.sol:22"
          },
          {
            "label": "__gap",
            "offset": 0,
            "slot": "52",
            "type": "t_array(t_uint256)49_storage",
            "contract": "OwnableUpgradeable",
            "src": "@openzeppelin/contracts-upgradeable/access/OwnableUpgradeable.sol:87"
          },
          {
            "label": "handlerAddress",
            "offset": 0,
            "slot": "101",
            "type": "t_address",
            "contract": "ContractNFTFactory",
            "src": "contracts/ContractNFTFactory.sol:13"
          },
          {
            "label": "erc721Implementation",
            "offset": 0,
            "slot": "102",
            "type": "t_address",
            "contract": "ContractNFTFactory",
            "src": "contracts/ContractNFTFactory.sol:14"
          },
          {
            "label": "ERC721Clones",
            "offset": 0,
            "slot": "103",
            "type": "t_array(t_address)dyn_storage",
            "contract": "ContractNFTFactory",
            "src": "contracts/ContractNFTFactory.sol:17"
          }
        ],
        "types": {
          "t_address": {
            "label": "address",
            "numberOfBytes": "20"
          },
          "t_array(t_address)dyn_storage": {
            "label": "address[]",
            "numberOfBytes": "32"
          },
          "t_array(t_uint256)49_storage": {
            "label": "uint256[49]",
            "numberOfBytes": "1568"
          },
          "t_array(t_uint256)50_storage": {
            "label": "uint256[50]",
            "numberOfBytes": "1600"
          },
          "t_bool": {
            "label": "bool",
            "numberOfBytes": "1"
          },
          "t_uint256": {
            "label": "uint256",
            "numberOfBytes": "32"
          }
        }
      }
    },
    "4b096998c78fed39cd06dea37df1f83b27650c1bd05919d130c7b655e8af5581": {
      "address": "0x8F5def8Ed22999B2eD13Ca5C379a6eb42411b6f6",
      "txHash": "0xeb3202b784e93571b229be36398278c85c5cfa77e9c24c09d6bd0a4c58ed9c94",
      "layout": {
        "storage": [
          {
            "label": "_initialized",
            "offset": 0,
            "slot": "0",
            "type": "t_bool",
            "contract": "Initializable",
            "src": "@openzeppelin/contracts-upgradeable/proxy/utils/Initializable.sol:39"
          },
          {
            "label": "_initializing",
            "offset": 1,
            "slot": "0",
            "type": "t_bool",
            "contract": "Initializable",
            "src": "@openzeppelin/contracts-upgradeable/proxy/utils/Initializable.sol:44"
          },
          {
            "label": "__gap",
            "offset": 0,
            "slot": "1",
            "type": "t_array(t_uint256)50_storage",
            "contract": "ContextUpgradeable",
            "src": "@openzeppelin/contracts-upgradeable/utils/ContextUpgradeable.sol:36"
          },
          {
            "label": "_owner",
            "offset": 0,
            "slot": "51",
            "type": "t_address",
            "contract": "OwnableUpgradeable",
            "src": "@openzeppelin/contracts-upgradeable/access/OwnableUpgradeable.sol:22"
          },
          {
            "label": "__gap",
            "offset": 0,
            "slot": "52",
            "type": "t_array(t_uint256)49_storage",
            "contract": "OwnableUpgradeable",
            "src": "@openzeppelin/contracts-upgradeable/access/OwnableUpgradeable.sol:87"
          },
          {
            "label": "handlerAddress",
            "offset": 0,
            "slot": "101",
            "type": "t_address",
            "contract": "ContractNFTFactory",
            "src": "contracts/ContractNFTFactory.sol:13"
          },
          {
            "label": "erc721Implementation",
            "offset": 0,
            "slot": "102",
            "type": "t_address",
            "contract": "ContractNFTFactory",
            "src": "contracts/ContractNFTFactory.sol:14"
          },
          {
            "label": "ERC721Clones",
            "offset": 0,
            "slot": "103",
            "type": "t_array(t_address)dyn_storage",
            "contract": "ContractNFTFactory",
            "src": "contracts/ContractNFTFactory.sol:17"
          }
        ],
        "types": {
          "t_address": {
            "label": "address",
            "numberOfBytes": "20"
          },
          "t_array(t_address)dyn_storage": {
            "label": "address[]",
            "numberOfBytes": "32"
          },
          "t_array(t_uint256)49_storage": {
            "label": "uint256[49]",
            "numberOfBytes": "1568"
          },
          "t_array(t_uint256)50_storage": {
            "label": "uint256[50]",
            "numberOfBytes": "1600"
          },
          "t_bool": {
            "label": "bool",
            "numberOfBytes": "1"
          },
          "t_uint256": {
            "label": "uint256",
            "numberOfBytes": "32"
          }
        }
      }
    },
    "9baf2dbd3954c8cef38835a1b74c054b35337dbad72d208923c79b4b4e453f65": {
      "address": "0x6710105B8424f8691A2aeeA7173ec0b067d16cf2",
      "txHash": "0x26e0e6e8fc3b75e73381adf2147c84143dd5e12177289b02da6f50b0772bfe53",
      "layout": {
        "storage": [
          {
            "label": "_NOT_ENTERED",
            "offset": 0,
            "slot": "0",
            "type": "t_uint256",
            "contract": "ReentrancyGuardUpgradable",
            "src": "contracts/ReentrancyGuardUpgradable.sol:30"
          },
          {
            "label": "_ENTERED",
            "offset": 0,
            "slot": "1",
            "type": "t_uint256",
            "contract": "ReentrancyGuardUpgradable",
            "src": "contracts/ReentrancyGuardUpgradable.sol:31"
          },
          {
            "label": "_status",
            "offset": 0,
            "slot": "2",
            "type": "t_uint256",
            "contract": "ReentrancyGuardUpgradable",
            "src": "contracts/ReentrancyGuardUpgradable.sol:33"
          },
          {
            "label": "_initialized",
            "offset": 0,
            "slot": "3",
            "type": "t_bool",
            "contract": "Initializable",
            "src": "@openzeppelin/contracts-upgradeable/proxy/utils/Initializable.sol:39"
          },
          {
            "label": "_initializing",
            "offset": 1,
            "slot": "3",
            "type": "t_bool",
            "contract": "Initializable",
            "src": "@openzeppelin/contracts-upgradeable/proxy/utils/Initializable.sol:44"
          },
          {
            "label": "__gap",
            "offset": 0,
            "slot": "4",
            "type": "t_array(t_uint256)50_storage",
            "contract": "ContextUpgradeable",
            "src": "@openzeppelin/contracts-upgradeable/utils/ContextUpgradeable.sol:36"
          },
          {
            "label": "_owner",
            "offset": 0,
            "slot": "54",
            "type": "t_address",
            "contract": "OwnableUpgradeable",
            "src": "contracts/OwnableUpgradeable.sol:21"
          },
          {
            "label": "__gap",
            "offset": 0,
            "slot": "55",
            "type": "t_array(t_uint256)49_storage",
            "contract": "OwnableUpgradeable",
            "src": "contracts/OwnableUpgradeable.sol:77"
          },
          {
            "label": "byPassable",
            "offset": 0,
            "slot": "104",
            "type": "t_bool",
            "contract": "IsOverridableUpgradable",
            "src": "contracts/IsOverridableUpgradable.sol:6"
          },
          {
            "label": "byPassableFunction",
            "offset": 0,
            "slot": "105",
            "type": "t_mapping(t_address,t_mapping(t_bytes4,t_bool))",
            "contract": "IsOverridableUpgradable",
            "src": "contracts/IsOverridableUpgradable.sol:7"
          },
          {
            "label": "byPassableIds",
            "offset": 0,
            "slot": "106",
            "type": "t_mapping(t_address,t_mapping(t_uint256,t_bool))",
            "contract": "IsOverridableUpgradable",
            "src": "contracts/IsOverridableUpgradable.sol:8"
          },
          {
            "label": "registeredContracts",
            "offset": 0,
            "slot": "107",
            "type": "t_mapping(t_address,t_uint256)",
            "contract": "HasRegistrationUpgradable",
            "src": "contracts/HasRegistrationUpgradable.sol:6"
          },
          {
            "label": "registeredOfType",
            "offset": 0,
            "slot": "108",
            "type": "t_mapping(t_uint256,t_array(t_address)dyn_storage)",
            "contract": "HasRegistrationUpgradable",
            "src": "contracts/HasRegistrationUpgradable.sol:7"
          },
          {
            "label": "contractCount",
            "offset": 0,
            "slot": "109",
            "type": "t_uint256",
            "contract": "HasRegistrationUpgradable",
            "src": "contracts/HasRegistrationUpgradable.sol:9"
          },
          {
            "label": "canAddBalances",
            "offset": 0,
            "slot": "110",
            "type": "t_bool",
            "contract": "BalanceUpgradable",
            "src": "contracts/BalanceUpgradable.sol:8"
          },
          {
            "label": "usedNonces",
            "offset": 0,
            "slot": "111",
            "type": "t_mapping(t_uint256,t_bool)",
            "contract": "BalanceUpgradable",
            "src": "contracts/BalanceUpgradable.sol:9"
          },
          {
            "label": "balances",
            "offset": 0,
            "slot": "112",
            "type": "t_mapping(t_address,t_mapping(t_uint256,t_struct(Balances)2342_storage))",
            "contract": "BalanceUpgradable",
            "src": "contracts/BalanceUpgradable.sol:25"
          },
          {
            "label": "contractTokenIds",
            "offset": 0,
            "slot": "113",
            "type": "t_mapping(t_address,t_array(t_uint256)dyn_storage)",
            "contract": "BalanceUpgradable",
            "src": "contracts/BalanceUpgradable.sol:26"
          },
          {
            "label": "witnesses",
            "offset": 0,
            "slot": "114",
            "type": "t_mapping(t_address,t_mapping(t_address,t_bool))",
            "contract": "BalanceUpgradable",
            "src": "contracts/BalanceUpgradable.sol:27"
          },
          {
            "label": "tokensToContractMap",
            "offset": 0,
            "slot": "115",
            "type": "t_mapping(t_bytes32,t_mapping(t_address,t_array(t_uint256)dyn_storage))",
            "contract": "BalanceUpgradable",
            "src": "contracts/BalanceUpgradable.sol:28"
          }
        ],
        "types": {
          "t_address": {
            "label": "address",
            "numberOfBytes": "20"
          },
          "t_array(t_address)dyn_storage": {
            "label": "address[]",
            "numberOfBytes": "32"
          },
          "t_array(t_struct(BalanceObject)2337_storage)dyn_storage": {
            "label": "struct BalanceUpgradable.BalanceObject[]",
            "numberOfBytes": "32"
          },
          "t_array(t_uint256)49_storage": {
            "label": "uint256[49]",
            "numberOfBytes": "1568"
          },
          "t_array(t_uint256)50_storage": {
            "label": "uint256[50]",
            "numberOfBytes": "1600"
          },
          "t_array(t_uint256)dyn_storage": {
            "label": "uint256[]",
            "numberOfBytes": "32"
          },
          "t_bool": {
            "label": "bool",
            "numberOfBytes": "1"
          },
          "t_bytes32": {
            "label": "bytes32",
            "numberOfBytes": "32"
          },
          "t_bytes4": {
            "label": "bytes4",
            "numberOfBytes": "4"
          },
          "t_mapping(t_address,t_array(t_uint256)dyn_storage)": {
            "label": "mapping(address => uint256[])",
            "numberOfBytes": "32"
          },
          "t_mapping(t_address,t_bool)": {
            "label": "mapping(address => bool)",
            "numberOfBytes": "32"
          },
          "t_mapping(t_address,t_mapping(t_address,t_bool))": {
            "label": "mapping(address => mapping(address => bool))",
            "numberOfBytes": "32"
          },
          "t_mapping(t_address,t_mapping(t_bytes4,t_bool))": {
            "label": "mapping(address => mapping(bytes4 => bool))",
            "numberOfBytes": "32"
          },
          "t_mapping(t_address,t_mapping(t_uint256,t_bool))": {
            "label": "mapping(address => mapping(uint256 => bool))",
            "numberOfBytes": "32"
          },
          "t_mapping(t_address,t_mapping(t_uint256,t_struct(Balances)2342_storage))": {
            "label": "mapping(address => mapping(uint256 => struct BalanceUpgradable.Balances))",
            "numberOfBytes": "32"
          },
          "t_mapping(t_address,t_uint256)": {
            "label": "mapping(address => uint256)",
            "numberOfBytes": "32"
          },
          "t_mapping(t_bytes32,t_mapping(t_address,t_array(t_uint256)dyn_storage))": {
            "label": "mapping(bytes32 => mapping(address => uint256[]))",
            "numberOfBytes": "32"
          },
          "t_mapping(t_bytes4,t_bool)": {
            "label": "mapping(bytes4 => bool)",
            "numberOfBytes": "32"
          },
          "t_mapping(t_uint256,t_array(t_address)dyn_storage)": {
            "label": "mapping(uint256 => address[])",
            "numberOfBytes": "32"
          },
          "t_mapping(t_uint256,t_bool)": {
            "label": "mapping(uint256 => bool)",
            "numberOfBytes": "32"
          },
          "t_mapping(t_uint256,t_struct(Balances)2342_storage)": {
            "label": "mapping(uint256 => struct BalanceUpgradable.Balances)",
            "numberOfBytes": "32"
          },
          "t_string_storage": {
            "label": "string",
            "numberOfBytes": "32"
          },
          "t_struct(BalanceObject)2337_storage": {
            "label": "struct BalanceUpgradable.BalanceObject",
            "members": [
              {
                "label": "balance",
                "type": "t_uint256",
                "offset": 0,
                "slot": "0"
              },
              {
                "label": "blockchain",
                "type": "t_uint256",
                "offset": 0,
                "slot": "1"
              },
              {
                "label": "name",
                "type": "t_string_storage",
                "offset": 0,
                "slot": "2"
              },
              {
                "label": "symbol",
                "type": "t_string_storage",
                "offset": 0,
                "slot": "3"
              },
              {
                "label": "tokenId",
                "type": "t_uint256",
                "offset": 0,
                "slot": "4"
              },
              {
                "label": "_address",
                "type": "t_address",
                "offset": 0,
                "slot": "5"
              },
              {
                "label": "_type",
                "type": "t_uint256",
                "offset": 0,
                "slot": "6"
              }
            ],
            "numberOfBytes": "224"
          },
          "t_struct(Balances)2342_storage": {
            "label": "struct BalanceUpgradable.Balances",
            "members": [
              {
                "label": "balances",
                "type": "t_array(t_struct(BalanceObject)2337_storage)dyn_storage",
                "offset": 0,
                "slot": "0"
              }
            ],
            "numberOfBytes": "32"
          },
          "t_uint256": {
            "label": "uint256",
            "numberOfBytes": "32"
          }
        }
      }
    }
  }
}
